[
  { "id": 1,  "category": "main", "name": "소금구이 1kg",  "desc": "숯불에 구워내는 본연의 맛 소금구이",         "price": 33000, "badge": "추천" },
  { "id": 2,  "category": "main", "name": "양념구이 1kg",  "desc": "특제 양념으로 재운 쪽갈비",                  "price": 34000, "badge": "추천" },
  { "id": 3,  "category": "main", "name": "반반 쪽갈비",   "desc": "소금구이 + 양념구이 반반 구성",              "price": 34000, "badge": "" },
  { "id": 4,  "category": "main", "name": "마늘간장 1kg",  "desc": "고소한 마늘간장 양념 쪽갈비",               "price": 34000, "badge": "" },
  { "id": 5,  "category": "main", "name": "매콤바베큐 1kg","desc": "달콤하고 매콤한 바베큐 소스 쪽갈비",        "price": 34000, "badge": "" },
  { "id": 6,  "category": "main", "name": "양념반반",      "desc": "두 가지 양념을 한 번에",                    "price": 35000, "badge": "" },
  { "id": 7,  "category": "main", "name": "500g (소금/양념/마늘/매콤바베큐)", "desc": "1인분 500g — 4가지 맛 중 선택", "price": 17000, "badge": "1인" },
  { "id": 8,  "category": "side", "name": "양푼이도시락",  "desc": "",                                          "price": 5000,  "badge": "" },
  { "id": 9,  "category": "side", "name": "치즈추가",      "desc": "",                                          "price": 5000,  "badge": "" },
  { "id": 10, "category": "side", "name": "계란찜",        "desc": "",                                          "price": 4000,  "badge": "" },
  { "id": 11, "category": "side", "name": "공기밥",        "desc": "",                                          "price": 1000,  "badge": "" },
  { "id": 12, "category": "side", "name": "파인샤베트",    "desc": "",                                          "price": 7000,  "badge": "" },
  { "id": 13, "category": "meal", "name": "라면",          "desc": "",                                          "price": 4000,  "badge": "" },
  { "id": 14, "category": "meal", "name": "김치손수제비",  "desc": "",                                          "price": 6000,  "badge": "" },
  { "id": 15, "category": "meal", "name": "간장계란밥",    "desc": "",                                          "price": 3000,  "badge": "" },
  { "id": 16, "category": "meal", "name": "김치우동",      "desc": "",                                          "price": 7000,  "badge": "" }
]
